odoo/addons/account_payment_batch_process/README.rst
odoo/addons/account_payment_batch_process/__init__.py
odoo/addons/account_payment_batch_process/__manifest__.py
odoo/addons/account_payment_batch_process/i18n/account_payment_batch_process.pot
odoo/addons/account_payment_batch_process/i18n/pt.po
odoo/addons/account_payment_batch_process/models/__init__.py
odoo/addons/account_payment_batch_process/models/account_payment.py
odoo/addons/account_payment_batch_process/readme/CONTRIBUTORS.rst
odoo/addons/account_payment_batch_process/readme/DESCRIPTION.rst
odoo/addons/account_payment_batch_process/readme/USAGE.rst
odoo/addons/account_payment_batch_process/static/description/icon.png
odoo/addons/account_payment_batch_process/static/description/index.html
odoo/addons/account_payment_batch_process/views/invoice_view.xml
odoo/addons/account_payment_batch_process/wizard/__init__.py
odoo/addons/account_payment_batch_process/wizard/invoice_batch_process.py
odoo/addons/account_payment_batch_process/wizard/invoice_batch_process_view.xml
odoo11_addon_account_payment_batch_process-11.0.1.0.0.99.dev5.dist-info/METADATA
odoo11_addon_account_payment_batch_process-11.0.1.0.0.99.dev5.dist-info/WHEEL
odoo11_addon_account_payment_batch_process-11.0.1.0.0.99.dev5.dist-info/top_level.txt
odoo11_addon_account_payment_batch_process-11.0.1.0.0.99.dev5.dist-info/RECORD
